README.rst
setup.cfg
setup.py
Flask_OAuth2_Provider.egg-info/PKG-INFO
Flask_OAuth2_Provider.egg-info/SOURCES.txt
Flask_OAuth2_Provider.egg-info/dependency_links.txt
Flask_OAuth2_Provider.egg-info/requires.txt
Flask_OAuth2_Provider.egg-info/top_level.txt
flask_oauth2_provider/__init__.py
flask_oauth2_provider/exceptions.py
flask_oauth2_provider/provider.py
flask_oauth2_provider/schemata.py