Metadata-Version: 1.1
Name: Flask-OAuth2-Provider
Version: 0.1.1
Summary: A simple flask oauth2 provider
Home-page: https://github.com/apiwatcher/flask-ouath2-provider
Author: Karel Jakubec
Author-email: karel@jakubec.name
License: MIT
Keywords: oauth authentication authorization
Platform: UNKNOWN
Classifier: Development Status :: 2 - Pre-Alpha
Classifier: Framework :: Flask
Classifier: Intended Audience :: Developers
Classifier: Topic :: Software Development :: Libraries :: Python Modules
Classifier: License :: OSI Approved :: MIT License
Classifier: Programming Language :: Python :: 2
Classifier: Programming Language :: Python :: 2.7
